liquidhandling/CherryPicking.py
liquidhandling/Plates.py
liquidhandling/Properties.py
liquidhandling/VolumeManager.py
liquidhandling/__init__.py
liquidhandling/hudson/RapidPick.py
liquidhandling/hudson/SoftLinx.py
liquidhandling/hudson/SoloSoft.py
liquidhandling/hudson/__init__.py
liquidhandling-0.1.40.dist-info/LICENSE
liquidhandling-0.1.40.dist-info/METADATA
liquidhandling-0.1.40.dist-info/WHEEL
liquidhandling-0.1.40.dist-info/top_level.txt
liquidhandling-0.1.40.dist-info/RECORD
