Metadata-Version: 2.1
Name: liquidhandling
Version: 0.1.40
Summary: A python library developed to allow programmatic control of the Hudson Robotics systems installed in Argonne National Laboratory's Secure BIO Lab. 
Home-page: http://github.com/luckierdodge/liquidhandling
Author: Ryan D. Lewis
Author-email: ryan.lewis@anl.gov
License: MIT
Keywords: robotics laboratory automation biology
Requires-Python: >=3.8.5
License-File: LICENSE
Requires-Dist: jsonref
Requires-Dist: jsonschema
Requires-Dist: pytest
Requires-Dist: path
Requires-Dist: pandas
Requires-Dist: openpyxl
Requires-Dist: mysql-connector-python
Requires-Dist: zmq
